eodo2/__init__.py
eodo2/app.py
eodo2-0.1.21.dist-info/METADATA
eodo2-0.1.21.dist-info/WHEEL
eodo2-0.1.21.dist-info/entry_points.txt
eodo2-0.1.21.dist-info/top_level.txt
eodo2-0.1.21.dist-info/RECORD
