Metadata-Version: 2.4
Name: eodo2
Version: 0.1.21
Summary: EdgeOneDynamicOrigin
Requires-Python: >=3.12
Requires-Dist: fastapi<1.0,>=0.110
Requires-Dist: uvicorn<1.0,>=0.27
Requires-Dist: psutil<6.0,>=5.9
Requires-Dist: requests<3.0,>=2.31
Requires-Dist: PyYAML<7.0,>=6.0
Requires-Dist: schedule<2.0,>=1.2
